CONFIG.md
LICENSE
MANIFEST.in
README.md
config.ini.master
requirements.txt
setup.py
pyamihtmlx/__init__.py
pyamihtmlx/ami_bib.py
pyamihtmlx/ami_config.py
pyamihtmlx/ami_html.py
pyamihtmlx/ami_integrate.py
pyamihtmlx/ami_nlp.py
pyamihtmlx/ami_pdf.py
pyamihtmlx/ami_pdf_libs.py
pyamihtmlx/ami_svg.py
pyamihtmlx/ami_util.py
pyamihtmlx/bbox_copy.py
pyamihtmlx/display.py
pyamihtmlx/file_lib.py
pyamihtmlx/get_endpoint_html.py
pyamihtmlx/html_marker.py
pyamihtmlx/ipcc.py
pyamihtmlx/pyamix.py
pyamihtmlx/un.py
pyamihtmlx/util.py
pyamihtmlx/wikimedia.py
pyamihtmlx/xml_lib.py
pyamihtmlx.egg-info/PKG-INFO
pyamihtmlx.egg-info/SOURCES.txt
pyamihtmlx.egg-info/dependency_links.txt
pyamihtmlx.egg-info/entry_points.txt
pyamihtmlx.egg-info/not-zip-safe
pyamihtmlx.egg-info/requires.txt
pyamihtmlx.egg-info/top_level.txt
test/test_all.py
test/test_display.py
test/test_experiment.py
test/test_file.py
test/test_gui.py
test/test_headless.py
test/test_html.py
test/test_integrate.py
test/test_jeor.py
test/test_nlp.py
test/test_pdf.py
test/test_pyamix.py
test/test_svg.py
test/test_text.py
test/test_un.py
test/test_util.py
test/test_wikidata.py
test/test_xml.py