Metadata-Version: 2.1
Name: pyamihtmlx
Version: 0.1.5
Summary: pdf2html converter and enhancer
Home-page: https://github.com/petermr/pyamihtml
Author: Peter Murray-Rust
Author-email: petermurrayrust@googlemail.com
License: Apache2
Keywords: text and data mining
Classifier: Development Status :: 3 - Alpha
Classifier: Intended Audience :: Developers
Classifier: License :: OSI Approved :: Apache Software License
Classifier: Natural Language :: English
Classifier: Programming Language :: Python :: 3.4
Classifier: Programming Language :: Python :: 3.5
Classifier: Programming Language :: Python :: 3.6
Classifier: Programming Language :: Python :: 3.8
Requires-Python: >=3.7
License-File: LICENSE
Requires-Dist: lxml
Requires-Dist: nltk
Requires-Dist: pdfminer3
Requires-Dist: Pillow
Requires-Dist: setuptools
Requires-Dist: pdfplumber
Requires-Dist: requests
Requires-Dist: pyvis
